scmvae/__init__.py
scmvae/draw.py
scmvae/helper.py
scmvae/model.py
scmvae/pckinspector .py
scmvae/pckinspector.py
scmvae/pl.py
scmvae/preprocessing.py
scmvae-1.0.0.dist-info/LICENSE.txt
scmvae-1.0.0.dist-info/METADATA
scmvae-1.0.0.dist-info/WHEEL
scmvae-1.0.0.dist-info/top_level.txt
scmvae-1.0.0.dist-info/RECORD
