Metadata-Version: 2.1
Name: scmvae
Version: 1.0.0
Summary: a comprehensive single-cell multimodal analysis python package based on mixed variational autoencoder
Home-page: https://github.com/studentiz/scmvae
Author: studentiz
Author-email: studentiz@live.com
License: MIT
Platform: UNKNOWN
Classifier: License :: OSI Approved :: MIT License
Classifier: Programming Language :: Python
Classifier: Programming Language :: Python :: 3
Classifier: Programming Language :: Python :: 3.6
Classifier: Programming Language :: Python :: Implementation :: CPython
Classifier: Programming Language :: Python :: Implementation :: PyPy
Requires-Python: >=3.6.5
License-File: LICENSE.txt
Requires-Dist: cloudpickle (==1.6.0)
Requires-Dist: imgaug (==0.2.6)
Requires-Dist: scikit-learn
Requires-Dist: numpy
Requires-Dist: scikit-misc
Requires-Dist: leidenalg
Requires-Dist: phenograph
Requires-Dist: umap-learn
Requires-Dist: pandas
Requires-Dist: matplotlib
Requires-Dist: datashader
Requires-Dist: bokeh
Requires-Dist: holoviews
Requires-Dist: scikit-image
Requires-Dist: colorcet
Requires-Dist: scanpy
Requires-Dist: tensorflow
Requires-Dist: keras
Provides-Extra: cpu
Requires-Dist: tensorflow ; extra == 'cpu'
Provides-Extra: gpu
Requires-Dist: tensorflow-gpu ; extra == 'gpu'
